MANIFEST.in
setup.py
bin/ccwtool-cli
steptoolkit/__init__.py
steptoolkit.egg-info/PKG-INFO
steptoolkit.egg-info/SOURCES.txt
steptoolkit.egg-info/dependency_links.txt
steptoolkit.egg-info/not-zip-safe
steptoolkit.egg-info/requires.txt
steptoolkit.egg-info/top_level.txt
steptoolkit/ccwtool/__init__.py
steptoolkit/ccwtool/dataparser.py
steptoolkit/ccwtool/exchangerate.py
steptoolkit/ccwtool/xlsxextension.py
steptoolkit/ccwtool/images/logo.jpg