Metadata-Version: 1.1
Name: steptoolkit
Version: 0.3
Summary: The unofficial Python toolkit of Step Logic Ltd
Home-page: https://bitbucket.org/idrey/steptoolkit
Author: Ilya Drey
Author-email: ilya@drey.su
License: MIT
Platform: UNKNOWN
Classifier: Development Status :: 3 - Alpha
Classifier: License :: OSI Approved :: MIT License
Classifier: Programming Language :: Python :: 2.7
Classifier: Topic :: Software Development :: Libraries
